{
  "clicks": [
    {
      "id": "autozoom-0",
      "time": 1752428920.0725274,
      "x": 668.0,
      "y": 369.0,
      "width": 1920,
      "height": 1200,
      "zoomLevel": 2.0,
      "duration": 2.0,
      "type": "autozoom"
    },
    {
      "id": "autozoom-1",
      "time": 1752428922.0510383,
      "x": 501.0,
      "y": 700.0,
      "width": 1920,
      "height": 1200,
      "zoomLevel": 2.0,
      "duration": 2.0,
      "type": "autozoom"
    },
    {
      "id": "autozoom-2",
      "time": 1752428926.4100976,
      "x": 719.0,
      "y": 496.0,
      "width": 1920,
      "height": 1200,
      "zoomLevel": 2.0,
      "duration": 2.0,
      "type": "autozoom"
    },
    {
      "id": "autozoom-3",
      "time": 1752428929.1876428,
      "x": 1774.0,
      "y": 28.0,
      "width": 1920,
      "height": 1200,
      "zoomLevel": 2.0,
      "duration": 2.0,
      "type": "autozoom"
    },
    {
      "id": "autozoom-4",
      "time": 1752428932.927573,
      "x": 634.0,
      "y": 147.0,
      "width": 1920,
      "height": 1200,
      "zoomLevel": 2.0,
      "duration": 2.0,
      "type": "autozoom"
    },
    {
      "id": "autozoom-5",
      "time": 1752428934.2504883,
      "x": 635.0,
      "y": 147.0,
      "width": 1920,
      "height": 1200,
      "zoomLevel": 2.0,
      "duration": 2.0,
      "type": "autozoom"
    },
    {
      "id": "autozoom-6",
      "time": 1752428938.5413084,
      "x": 1121.0,
      "y": 1055.0,
      "width": 1920,
      "height": 1200,
      "zoomLevel": 2.0,
      "duration": 2.0,
      "type": "autozoom"
    },
    {
      "id": "autozoom-7",
      "time": 1752428940.3391764,
      "x": 464.0,
      "y": 528.0,
      "width": 1920,
      "height": 1200,
      "zoomLevel": 2.0,
      "duration": 2.0,
      "type": "autozoom"
    }
  ],
  "width": 1920,
  "height": 1200,
  "duration": 22.132781982421875,
  "fps": 30,
  "zoomFactor": 2.0,
  "zoomTime": 1.0,
  "idleTime": 1.0,
  "totalClicks": 8,
  "exportedAt": 1752428945.7584896
}